mario/__init__.py
mario/cluster.py
mario/embed.py
mario/match.py
mario/match_utils.py
mario/utils.py
pyMARIO-0.0.2.dist-info/LICENSE.txt
pyMARIO-0.0.2.dist-info/METADATA
pyMARIO-0.0.2.dist-info/WHEEL
pyMARIO-0.0.2.dist-info/top_level.txt
pyMARIO-0.0.2.dist-info/RECORD
