Metadata-Version: 2.1
Name: pyMARIO
Version: 0.0.2
Summary: A package for matching and integrating multi-modal single cell data with shared and distinct features
Home-page: https://github.com/shuxiaoc/mario-py
Author: Shuxiao Chen, Bokai Zhu
Author-email: shuxiaoc@wharton.upenn.edu, bkzhu@stanford.edu
License: UNKNOWN
Project-URL: Bug Tracker, https://github.com/shuxiaoc/mario-py/issues
Platform: UNKNOWN
Classifier: Programming Language :: Python :: 3
Classifier: Operating System :: OS Independent
Requires-Python: >=3.8
License-File: LICENSE.txt
Requires-Dist: numpy (==1.20.1)
Requires-Dist: pandas (==1.2.1)
Requires-Dist: scipy (==1.6.2)
Requires-Dist: scikit-learn (==0.23.2)
Requires-Dist: matplotlib (>=3.3.4)
Requires-Dist: seaborn (>=0.11.1)
